lascar/__init__.py
lascar/session.py
lascar/container/__init__.py
lascar/container/container.py
lascar/container/filtered_container.py
lascar/container/hdf5_container.py
lascar/container/multiple_container.py
lascar/container/npy_container.py
lascar/container/simulation_container.py
lascar/container/trace.py
lascar/engine/__init__.py
lascar/engine/chi2test_engine.py
lascar/engine/classifier_engine.py
lascar/engine/cpa_engine.py
lascar/engine/dom_engine.py
lascar/engine/dpa_engine.py
lascar/engine/engine.py
lascar/engine/guess_engine.py
lascar/engine/lra_engine.py
lascar/engine/nicv_engine.py
lascar/engine/partitioner_engine.py
lascar/engine/snr_engine.py
lascar/engine/ttest_engine.py
lascar/output/__init__.py
lascar/output/console_output_method.py
lascar/output/hdf5_output_method.py
lascar/output/output_method.py
lascar/output/parse_results.py
lascar/output/pickle_output_method.py
lascar/output/plot_output_method.py
lascar/output/rank_estimation.py
lascar/output/table_output_method.py
lascar/plotting/__init__.py
lascar/plotting/plot.py
lascar/tools/__init__.py
lascar/tools/aes.py
lascar/tools/keras_neural_networks.py
lascar/tools/leakage_model.py
lascar/tools/numba_aes.py
lascar/tools/processing.py
lascar/tools/signal_processing.py
scripts/__init__.py
scripts/lascarctl.py
tests/__init__.py
tests/test_container.py
tests/test_engine.py
tests/test_hdf5_container.py
tests/test_numpy_container.py
tests/test_processing.py
tests/test_session.py
lascar-1.1.dist-info/METADATA
lascar-1.1.dist-info/WHEEL
lascar-1.1.dist-info/entry_points.txt
lascar-1.1.dist-info/top_level.txt
lascar-1.1.dist-info/RECORD
