Metadata-Version: 2.1
Name: lascar
Version: 1.1
Summary: Toolsuite for side-channel acquisition, container and analysis
Home-page: https://github.com/Ledger-Donjon/lascar
Author: Charles Guillemet, Manuel San Pedro, Victor Servant
Author-email: Manuel San Pedro <manuel.sanpedro@ledger.fr>, Victor Servant <victor.servant@ledger.fr>, Charles Guillemet <charles@ledger.fr>
Project-URL: Homepage, https://github.com/Ledger-Donjon/lascar
Project-URL: Bug Tracker, https://github.com/Ledger-Donjon/lascar/issues
Classifier: Programming Language :: Python :: 3
Classifier: License :: OSI Approved :: GNU Lesser General Public License v3 (LGPLv3)
Classifier: Operating System :: OS Independent
Requires-Python: >=3.0
Requires-Dist: click
Requires-Dist: numpy (>=1.17)
Requires-Dist: h5py
Requires-Dist: matplotlib
Requires-Dist: vispy
Requires-Dist: scikit-learn
Requires-Dist: scipy
Requires-Dist: keras
Requires-Dist: progressbar2
Requires-Dist: pytest
Requires-Dist: numba
Requires-Dist: psutil
